contfrac.py
ContFrac-1.0.0.dist-info/LICENSE.md
ContFrac-1.0.0.dist-info/METADATA
ContFrac-1.0.0.dist-info/WHEEL
ContFrac-1.0.0.dist-info/top_level.txt
ContFrac-1.0.0.dist-info/RECORD
