Metadata-Version: 2.1
Name: ContFrac
Version: 1.0.0
Summary: Continued fractions and convergents
Home-page: https://github.com/TheMatjaz/contfrac
Author: Matjaž Guštin
Author-email: dev@matjaz.it
License: BSD
Keywords: continued,fraction,fractions,convergent,rational
Platform: UNKNOWN
Classifier: Development Status :: 5 - Production/Stable
Classifier: Intended Audience :: Developers
Classifier: Intended Audience :: Science/Research
Classifier: License :: OSI Approved :: BSD License
Classifier: Topic :: Scientific/Engineering :: Mathematics
Classifier: Programming Language :: Python :: 3
Classifier: Programming Language :: Python :: 3.4
Classifier: Programming Language :: Python :: 3.5
Classifier: Programming Language :: Python :: 3.6
Classifier: Programming Language :: Python :: 3.7
Requires-Python: >=3
